gapper/__init__.py
gapper/__main__.py
gapper/_version.py
gapper/cli/__init__.py
gapper/cli/app.py
gapper/cli/check.py
gapper/cli/cli_options.py
gapper/cli/gen.py
gapper/cli/login.py
gapper/cli/rich_test_check_output.py
gapper/cli/rich_test_result_output.py
gapper/cli/run.py
gapper/cli/run_in_prod.py
gapper/cli/upload.py
gapper/cli/utils.py
gapper/connect/__init__.py
gapper/connect/api/__init__.py
gapper/connect/api/account.py
gapper/connect/api/assignment.py
gapper/connect/api/course.py
gapper/connect/api/mixins.py
gapper/connect/api/utils.py
gapper/connect/gui/__init__.py
gapper/connect/gui/_test_app.py
gapper/connect/gui/app_ui.py
gapper/connect/gui/assignments_ui.py
gapper/connect/gui/autograder_upload_ui.py
gapper/connect/gui/autograder_upload_ui.tcss
gapper/connect/gui/course_assignment_ui.py
gapper/connect/gui/courses_assignment_ui.tcss
gapper/connect/gui/login_ui.py
gapper/connect/gui/login_ui.tcss
gapper/connect/gui/messages.py
gapper/connect/gui/upload_app_ui.py
gapper/connect/gui/utils.py
gapper/core/__init__.py
gapper/core/errors.py
gapper/core/file_handlers.py
gapper/core/hook.py
gapper/core/injection.py
gapper/core/pipeline_support.py
gapper/core/problem/__init__.py
gapper/core/problem/extras/__init__.py
gapper/core/problem/extras/gradescope_connect.py
gapper/core/problem/problem_config.py
gapper/core/problem/problem_def.py
gapper/core/result_synthesizer.py
gapper/core/test_parameter.py
gapper/core/test_result.py
gapper/core/tester/__init__.py
gapper/core/tester/tester_def.py
gapper/core/tester/tester_hooks.py
gapper/core/types.py
gapper/core/unittest_wrapper/__init__.py
gapper/core/unittest_wrapper/utils.py
gapper/core/unittest_wrapper/wrapper_def.py
gapper/core/unittest_wrapper/wrapper_hooks.py
gapper/core/utils.py
gapper/gradescope/__init__.py
gapper/gradescope/datatypes/__init__.py
gapper/gradescope/datatypes/gradescope_meta.py
gapper/gradescope/datatypes/gradescope_output.py
gapper/gradescope/main.py
gapper/gradescope/resources/requirements.txt
gapper-1.4.0.dist-info/LICENSE
gapper-1.4.0.dist-info/METADATA
gapper-1.4.0.dist-info/WHEEL
gapper-1.4.0.dist-info/entry_points.txt
gapper-1.4.0.dist-info/RECORD
