Metadata-Version: 2.1
Name: gapper
Version: 1.4.0
Summary: Gradescope Autograder Packer
Home-page: https://github.com/FlickerSoul/gapper
License: MIT
Author: Heyuan Zeng
Author-email: hi@universe.observer
Requires-Python: >=3.12,<4.0
Classifier: License :: OSI Approved :: MIT License
Classifier: Programming Language :: Python :: 3
Classifier: Programming Language :: Python :: 3.12
Requires-Dist: beautifulsoup4 (>=4.12.2,<5.0.0)
Requires-Dist: dacite (>=1.8.1,<2.0.0)
Requires-Dist: dataclasses-json (>=0.6.1,<0.7.0)
Requires-Dist: dill (>=0.3.7,<0.4.0)
Requires-Dist: jinja2 (>=3.1.2,<4.0.0)
Requires-Dist: pytest (>=7.4.3,<8.0.0)
Requires-Dist: pyyaml (>=6.0.1,<7.0.0)
Requires-Dist: requests (>=2.31.0,<3.0.0)
Requires-Dist: requests-toolbelt (>=1.0.0,<2.0.0)
Requires-Dist: rich (>=13.6.0,<14.0.0)
Requires-Dist: textual (>=0.41.0,<0.42.0)
Requires-Dist: typer (>=0.9.0,<0.10.0)
Project-URL: Documentation, https://gapper.universe.observer
Project-URL: Repository, https://github.com/FlickerSoul/gapper
